aws_orbit/__init__.py
aws_orbit/__main__.py
aws_orbit/__metadata__.py
aws_orbit/bundle.py
aws_orbit/cdk.py
aws_orbit/cleanup.py
aws_orbit/docker.py
aws_orbit/exceptions.py
aws_orbit/k8s.py
aws_orbit/messages.py
aws_orbit/py.typed
aws_orbit/remote.py
aws_orbit/sh.py
aws_orbit/toolkit.py
aws_orbit/utils.py
aws_orbit/commands/__init__.py
aws_orbit/commands/build.py
aws_orbit/commands/delete.py
aws_orbit/commands/deploy.py
aws_orbit/commands/destroy.py
aws_orbit/commands/init.py
aws_orbit/commands/list.py
aws_orbit/commands/run.py
aws_orbit/data/charts/uninstall_namespace_charts.sh
aws_orbit/data/charts/team/team-space/.helmignore
aws_orbit/data/charts/team/team-space/Chart.yaml
aws_orbit/data/charts/team/team-space/values.yaml
aws_orbit/data/charts/team/team-space/templates/_helpers.tpl
aws_orbit/data/charts/team/team-space/templates/init-efs-job.yaml
aws_orbit/data/charts/team/team-space/templates/pod-setting-common.yaml
aws_orbit/data/charts/team/team-space/templates/pod-setting-notebook-profiles.yaml
aws_orbit/data/charts/team/team-space/templates/pod-setting-profile-examples.yaml
aws_orbit/data/charts/team/team-space/templates/pod-setting-runner-support.yaml
aws_orbit/data/charts/user/user-space/.helmignore
aws_orbit/data/charts/user/user-space/Chart.yaml
aws_orbit/data/charts/user/user-space/values.yaml
aws_orbit/data/charts/user/user-space/templates/_helpers.tpl
aws_orbit/data/charts/user/user-space/templates/copy_vscode_ext.yaml
aws_orbit/data/charts/user/user-space/templates/kubeflow_profile.yaml
aws_orbit/data/charts/user/user-space/templates/persistent.yaml
aws_orbit/data/charts/user/user-space/templates/roles.yaml
aws_orbit/data/charts/user/user-space/templates/security_policy.yaml
aws_orbit/data/cms/schema/Beneficiary_Summary.json
aws_orbit/data/cms/schema/Carrier_Claims.json
aws_orbit/data/cms/schema/Inpatient_Claims.json
aws_orbit/data/cms/schema/Outpatient_Claims.json
aws_orbit/data/cms/schema/Prescription_Drug_Events.json
aws_orbit-1.4.0.dist-info/LICENSE
aws_orbit-1.4.0.dist-info/METADATA
aws_orbit-1.4.0.dist-info/NOTICE
aws_orbit-1.4.0.dist-info/VERSION
aws_orbit-1.4.0.dist-info/WHEEL
aws_orbit-1.4.0.dist-info/entry_points.txt
aws_orbit-1.4.0.dist-info/top_level.txt
aws_orbit-1.4.0.dist-info/RECORD
